asttokunparse/__init__.py
asttokunparse/printer.py
asttokunparse/unparser.py
asttokunparse-2.0.0.dist-info/AUTHORS.rst
asttokunparse-2.0.0.dist-info/LICENSE
asttokunparse-2.0.0.dist-info/METADATA
asttokunparse-2.0.0.dist-info/WHEEL
asttokunparse-2.0.0.dist-info/top_level.txt
asttokunparse-2.0.0.dist-info/RECORD
