Metadata-Version: 2.1
Name: asttokunparse
Version: 2.0.0
Summary: An AST unparser for Python with tokenization
Home-page: https://github.com/gonglinyuan/asttokunparse
Maintainer: Linyuan Gong
Maintainer-email: gonglinyuan@hotmail.com
License: BSD
Keywords: asttokunparse
Platform: UNKNOWN
Classifier: Development Status :: 5 - Production/Stable
Classifier: Intended Audience :: Developers
Classifier: License :: OSI Approved :: BSD License
Classifier: Natural Language :: English
Classifier: Programming Language :: Python :: 3.8
Classifier: Topic :: Software Development :: Code Generators
License-File: LICENSE
License-File: AUTHORS.rst
Requires-Dist: wheel (<1.0,>=0.23.0)
Requires-Dist: astunparse
